LICENSE.txt
README.rst
setup.py
bin/debug.sh
linsharecli/__init__.py
linsharecli.egg-info/PKG-INFO
linsharecli.egg-info/SOURCES.txt
linsharecli.egg-info/dependency_links.txt
linsharecli.egg-info/entry_points.txt
linsharecli.egg-info/requires.txt
linsharecli.egg-info/top_level.txt
linsharecli/admin/__init__.py
linsharecli/admin/authentication.py
linsharecli/admin/core.py
linsharecli/admin/domain.py
linsharecli/admin/domainpolicies.py
linsharecli/admin/dpattern.py
linsharecli/admin/func.py
linsharecli/admin/iuser.py
linsharecli/admin/jwt.py
linsharecli/admin/ldap.py
linsharecli/admin/mail_activations.py
linsharecli/admin/mail_attachments.py
linsharecli/admin/mail_configs.py
linsharecli/admin/public_keys.py
linsharecli/admin/shared_space_members.py
linsharecli/admin/shared_spaces.py
linsharecli/admin/threads.py
linsharecli/admin/tmembers.py
linsharecli/admin/upgrade_tasks.py
linsharecli/admin/user.py
linsharecli/admin/welcome_messages.py
linsharecli/common/__init__.py
linsharecli/common/actions.py
linsharecli/common/cell.py
linsharecli/common/core.py
linsharecli/common/tables.py
linsharecli/tests/__init__.py
linsharecli/tests/core.py
linsharecli/tests/documents.py
linsharecli/tests/misc.py
linsharecli/tests/threads.py
linsharecli/user/__init__.py
linsharecli/user/audit.py
linsharecli/user/contactslists.py
linsharecli/user/contactslistscontacts.py
linsharecli/user/core.py
linsharecli/user/documents.py
linsharecli/user/guests.py
linsharecli/user/jwt.py
linsharecli/user/rshares.py
linsharecli/user/shared_space_audit.py
linsharecli/user/shared_space_members.py
linsharecli/user/shared_spaces.py
linsharecli/user/shares.py
linsharecli/user/users.py
linsharecli/user/wg_documents.py
linsharecli/user/wg_members.py
linsharecli/user/workgroups.py