Metadata-Version: 2.1
Name: linsharecli
Version: 1.1.3
Summary: LinShare command line interface.
Home-page: https://github.com/fred49/linshare-cli
Author: Frederic MARTIN
Author-email: frederic.martin.fma@gmail.com
License: GPL3
Classifier: Development Status :: 4 - Beta
Classifier: Intended Audience :: Developers
Classifier: Topic :: Software Development :: Build Tools
Classifier: Environment :: Console
Classifier: License :: OSI Approved :: GNU General Public License v3 (GPLv3)
Classifier: Programming Language :: Python :: 2.6
Classifier: Programming Language :: Python :: 2.7
License-File: LICENSE.txt
